setup.py
distributions_EH/Binomialdistribution.py
distributions_EH/Gaussiandistribution.py
distributions_EH/Generaldistribution.py
distributions_EH/__init__.py
distributions_EH.egg-info/PKG-INFO
distributions_EH.egg-info/SOURCES.txt
distributions_EH.egg-info/dependency_links.txt
distributions_EH.egg-info/not-zip-safe
distributions_EH.egg-info/top_level.txt