Metadata-Version: 1.0
Name: distributions-EH
Version: 0.2
Summary: Gaussian and Binomial distributions
Home-page: UNKNOWN
Author: Erkan Hatipoglu
Author-email: e109261@gmail.com
License: UNKNOWN
Platform: UNKNOWN
